velocem-0.0.12.data/platlib/velocem.pyd
velocem-0.0.12.dist-info/METADATA
velocem-0.0.12.dist-info/UsageLicense
velocem-0.0.12.dist-info/WHEEL
velocem-0.0.12.dist-info/entry_points.txt
velocem-0.0.12.dist-info/RECORD
