Metadata-Version: 2.1
Name: velocem
Version: 0.0.12
Summary: Hyperspeed Python Web Framework
Keywords: WSGI
Author-Email: Vito Gamberini <vito@gamberini.email>
License: Copyright (c) Vito Gamberini and Contributors
Classifier: Development Status :: 2 - Pre-Alpha
Classifier: License :: OSI Approved :: MIT No Attribution License (MIT-0)
Classifier: Programming Language :: Python :: 3
Classifier: Programming Language :: Python :: 3.12
Classifier: Operating System :: POSIX :: Linux
Classifier: Operating System :: Microsoft :: Windows
Classifier: Operating System :: MacOS
Project-URL: Documentation, https://github.com/nickelpro/velocem
Requires-Python: >=3.12
